{
  "trade_date": "20260313",
  "verify_date": "20260316",
  "gate": {
    "pass": true,
    "E1": 59,
    "E2": 0.0,
    "E3": 0,
    "EmotionScore": 0.4975,
    "EmotionSmooth": 0.4975,
    "EmotionWeight": 0.8985,
    "reason": "连板得分:0.00, 炸板得分:1.00, 活跃度得分:0.74, 情绪:0.50",
    "prev_emotion_smooth": 0.4975,
    "regime": {
      "score": 0.4975,
      "smooth": 0.4975,
      "weight": 0.8985,
      "state": "neutral",
      "inputs": {
        "E1": 59,
        "E2": 0.0,
        "E3": 0
      },
      "components": {
        "E3": 0.0,
        "E2": 1.0,
        "E1": 0.7375
      },
      "reason": "连板得分:0.00, 炸板得分:1.00, 活跃度得分:0.74, 情绪:0.50",
      "prev_smooth": 0.4975,
      "features": {
        "regime_score": 0.4975,
        "regime_smooth": 0.4975,
        "regime_weight": 0.8985
      },
      "scale": {
        "strength_scale": 0.8985
      },
      "calib": {
        "final_score_scale": 0.8985,
        "prob_scale": 0.8985
      }
    },
    "run_mode": "auto_daily"
  },
  "topN": [
    {
      "rank": 1,
      "ts_code": "002445.SZ",
      "name": "中南文化",
      "board": "钢加工",
      "StrengthScore": 43.644068,
      "ThemeBoost": 0.0,
      "prob_rule": 0.531314270719221,
      "prob_ml": 0.6340905728744572,
      "prob_final": 0.6340905728744572,
      "Probability": 0.6340905728744572,
      "final_score": 0.5311515370121201,
      "score": 0.5311515370121201,
      "prob": 0.6340905728744572,
      "strength01": 0.43644067999999997,
      "theme01": 0.0,
      "trade_date": "20260313",
      "seal_amount": 487232888.0,
      "open_times": 0.0,
      "turnover_rate": 7.7207,
      "prob_src": "ml",
      "prob_ml_available": true,
      "prob_fusion_mode": "ml_first",
      "run_mode": "auto_daily",
      "run_time_utc": "2026-03-15T08:11:01Z",
      "industry": "钢加工",
      "limit_type": "U",
      "close": "4.49",
      "up_limit": "4.49",
      "down_limit": "3.67",
      "fd_amount": "487232888.0",
      "first_time": "92500",
      "last_time": "92500",
      "题材加成": 0.0,
      "板块": "钢加工"
    },
    {
      "rank": 2,
      "ts_code": "600722.SH",
      "name": "金牛化工",
      "board": "化工原料",
      "StrengthScore": 48.508475,
      "ThemeBoost": 1.0,
      "prob_rule": 0.5021977910684783,
      "prob_ml": 0.5039595290743865,
      "prob_final": 0.5039595290743865,
      "Probability": 0.5039595290743865,
      "final_score": 0.5267116972751476,
      "score": 0.5267116972751476,
      "prob": 0.5039595290743865,
      "strength01": 0.48508474999999995,
      "theme01": 0.7692307692307692,
      "trade_date": "20260313",
      "seal_amount": 25104402.0,
      "open_times": 19.0,
      "turnover_rate": 59.4514,
      "prob_src": "ml",
      "prob_ml_available": true,
      "prob_fusion_mode": "ml_first",
      "run_mode": "auto_daily",
      "run_time_utc": "2026-03-15T08:11:01Z",
      "industry": "化工原料",
      "limit_type": "U",
      "close": "16.94",
      "up_limit": "16.94",
      "down_limit": "13.86",
      "fd_amount": "25104402.0",
      "first_time": "94004",
      "last_time": "144849",
      "题材加成": 1.0,
      "板块": "化工原料"
    },
    {
      "rank": 3,
      "ts_code": "003027.SZ",
      "name": "同兴科技",
      "board": "环境保护",
      "StrengthScore": 52.254237,
      "ThemeBoost": 0.04865851676579642,
      "prob_rule": 0.6151064406701515,
      "prob_ml": 0.5344864266829616,
      "prob_final": 0.5344864266829616,
      "Probability": 0.5344864266829616,
      "final_score": 0.4823919355062114,
      "score": 0.4823919355062114,
      "prob": 0.5344864266829616,
      "strength01": 0.52254237,
      "theme01": 0.03742962828138186,
      "trade_date": "20260313",
      "seal_amount": 107000572.0,
      "open_times": 0.0,
      "turnover_rate": 13.8841,
      "prob_src": "ml",
      "prob_ml_available": true,
      "prob_fusion_mode": "ml_first",
      "run_mode": "auto_daily",
      "run_time_utc": "2026-03-15T08:11:01Z",
      "industry": "环境保护",
      "limit_type": "U",
      "close": "24.52",
      "up_limit": "24.52",
      "down_limit": "20.06",
      "fd_amount": "107000572.0",
      "first_time": "105245",
      "last_time": "105245",
      "题材加成": 0.04865851676579642,
      "板块": "环境保护"
    },
    {
      "rank": 4,
      "ts_code": "600307.SH",
      "name": "酒钢宏兴",
      "board": "普钢",
      "StrengthScore": 62.254237,
      "ThemeBoost": 0.08,
      "prob_rule": 0.601087505930745,
      "prob_ml": 0.3619317627362545,
      "prob_final": 0.3619317627362545,
      "Probability": 0.3619317627362545,
      "final_score": 0.38401455406922436,
      "score": 0.38401455406922436,
      "prob": 0.3619317627362545,
      "strength01": 0.62254237,
      "theme01": 0.061538461538461535,
      "trade_date": "20260313",
      "seal_amount": 51620394.0,
      "open_times": 4.0,
      "turnover_rate": 16.5461,
      "prob_src": "ml",
      "prob_ml_available": true,
      "prob_fusion_mode": "ml_first",
      "run_mode": "auto_daily",
      "run_time_utc": "2026-03-15T08:11:01Z",
      "industry": "普钢",
      "limit_type": "U",
      "close": "2.22",
      "up_limit": "2.22",
      "down_limit": "1.82",
      "fd_amount": "51620394.0",
      "first_time": "93459",
      "last_time": "131441",
      "题材加成": 0.08,
      "板块": "普钢"
    },
    {
      "rank": 5,
      "ts_code": "600691.SH",
      "name": "潞化科技",
      "board": "农药化肥",
      "StrengthScore": 76.728814,
      "ThemeBoost": 0.44012104274902347,
      "prob_rule": 0.7023956625543502,
      "prob_ml": 0.2524007518294422,
      "prob_final": 0.2524007518294422,
      "Probability": 0.2524007518294422,
      "final_score": 0.3639936191074576,
      "score": 0.3639936191074576,
      "prob": 0.2524007518294422,
      "strength01": 0.76728814,
      "theme01": 0.3385546482684796,
      "trade_date": "20260313",
      "seal_amount": 106234341.0,
      "open_times": 1.0,
      "turnover_rate": 5.9848,
      "prob_src": "ml",
      "prob_ml_available": true,
      "prob_fusion_mode": "ml_first",
      "run_mode": "auto_daily",
      "run_time_utc": "2026-03-15T08:11:01Z",
      "industry": "农药化肥",
      "limit_type": "U",
      "close": "4.43",
      "up_limit": "4.43",
      "down_limit": "3.63",
      "fd_amount": "106234341.0",
      "first_time": "92504",
      "last_time": "93022",
      "题材加成": 0.44012104274902347,
      "板块": "农药化肥"
    },
    {
      "rank": 6,
      "ts_code": "603929.SH",
      "name": "亚翔集成",
      "board": "装修装饰",
      "StrengthScore": 66.728814,
      "ThemeBoost": 0.0,
      "prob_rule": 0.5998609578269766,
      "prob_ml": 0.2965521413747995,
      "prob_final": 0.2965521413747995,
      "Probability": 0.2965521413747995,
      "final_score": 0.3410441269623597,
      "score": 0.3410441269623597,
      "prob": 0.2965521413747995,
      "strength01": 0.66728814,
      "theme01": 0.0,
      "trade_date": "20260313",
      "seal_amount": 219353146.0,
      "open_times": 0.0,
      "turnover_rate": 2.6811,
      "prob_src": "ml",
      "prob_ml_available": true,
      "prob_fusion_mode": "ml_first",
      "run_mode": "auto_daily",
      "run_time_utc": "2026-03-15T08:11:01Z",
      "industry": "装修装饰",
      "limit_type": "U",
      "close": "140.83",
      "up_limit": "140.83",
      "down_limit": "115.23",
      "fd_amount": "219353146.0",
      "first_time": "93000",
      "last_time": "93000",
      "题材加成": 0.0,
      "板块": "装修装饰"
    },
    {
      "rank": 7,
      "ts_code": "002109.SZ",
      "name": "兴化股份",
      "board": "化工原料",
      "StrengthScore": 67.067797,
      "ThemeBoost": 1.0,
      "prob_rule": 0.8021747448733817,
      "prob_ml": 0.15987259568054218,
      "prob_final": 0.15987259568054218,
      "Probability": 0.15987259568054218,
      "final_score": 0.3229694878994565,
      "score": 0.3229694878994565,
      "prob": 0.15987259568054218,
      "strength01": 0.67067797,
      "theme01": 0.7692307692307692,
      "trade_date": "20260313",
      "seal_amount": 33441422.0,
      "open_times": 1.0,
      "turnover_rate": 17.175,
      "prob_src": "ml",
      "prob_ml_available": true,
      "prob_fusion_mode": "ml_first",
      "run_mode": "auto_daily",
      "run_time_utc": "2026-03-15T08:11:01Z",
      "industry": "化工原料",
      "limit_type": "U",
      "close": "5.18",
      "up_limit": "5.18",
      "down_limit": "4.24",
      "fd_amount": "33441422.0",
      "first_time": "93200",
      "last_time": "100521",
      "题材加成": 1.0,
      "板块": "化工原料"
    },
    {
      "rank": 8,
      "ts_code": "600121.SH",
      "name": "郑州煤电",
      "board": "煤炭开采",
      "StrengthScore": 65.40678,
      "ThemeBoost": 0.08,
      "prob_rule": 0.6650702421147496,
      "prob_ml": 0.25847997947970686,
      "prob_final": 0.25847997947970686,
      "Probability": 0.25847997947970686,
      "final_score": 0.317903391789641,
      "score": 0.317903391789641,
      "prob": 0.25847997947970686,
      "strength01": 0.6540678,
      "theme01": 0.061538461538461535,
      "trade_date": "20260313",
      "seal_amount": 170038778.0,
      "open_times": 0.0,
      "turnover_rate": 12.2185,
      "prob_src": "ml",
      "prob_ml_available": true,
      "prob_fusion_mode": "ml_first",
      "run_mode": "auto_daily",
      "run_time_utc": "2026-03-15T08:11:01Z",
      "industry": "煤炭开采",
      "limit_type": "U",
      "close": "5.65",
      "up_limit": "5.65",
      "down_limit": "4.63",
      "fd_amount": "170038778.0",
      "first_time": "92500",
      "last_time": "92500",
      "题材加成": 0.08,
      "板块": "煤炭开采"
    },
    {
      "rank": 9,
      "ts_code": "603538.SH",
      "name": "美诺华",
      "board": "化学制药",
      "StrengthScore": 46.932203,
      "ThemeBoost": 0.0,
      "prob_rule": 0.5880845140770732,
      "prob_ml": 0.25435671439910934,
      "prob_final": 0.25435671439910934,
      "Probability": 0.25435671439910934,
      "final_score": 0.2719141060793766,
      "score": 0.2719141060793766,
      "prob": 0.25435671439910934,
      "strength01": 0.46932203,
      "theme01": 0.0,
      "trade_date": "20260313",
      "seal_amount": 112124186.0,
      "open_times": 0.0,
      "turnover_rate": 14.3082,
      "prob_src": "ml",
      "prob_ml_available": true,
      "prob_fusion_mode": "ml_first",
      "run_mode": "auto_daily",
      "run_time_utc": "2026-03-15T08:11:01Z",
      "industry": "化学制药",
      "limit_type": "U",
      "close": "25.37",
      "up_limit": "25.37",
      "down_limit": "20.75",
      "fd_amount": "112124186.0",
      "first_time": "112950",
      "last_time": "112950",
      "题材加成": 0.0,
      "板块": "化学制药"
    },
    {
      "rank": 10,
      "ts_code": "601218.SH",
      "name": "吉鑫科技",
      "board": "电气设备",
      "StrengthScore": 50.118644,
      "ThemeBoost": 0.7946272018253463,
      "prob_rule": 0.6128322643257663,
      "prob_ml": 0.1392663227431279,
      "prob_final": 0.1392663227431279,
      "Probability": 0.1392663227431279,
      "final_score": 0.25884888329137007,
      "score": 0.25884888329137007,
      "prob": 0.1392663227431279,
      "strength01": 0.50118644,
      "theme01": 0.6112516937118049,
      "trade_date": "20260313",
      "seal_amount": 49132424.0,
      "open_times": 2.0,
      "turnover_rate": 31.6714,
      "prob_src": "ml",
      "prob_ml_available": true,
      "prob_fusion_mode": "ml_first",
      "run_mode": "auto_daily",
      "run_time_utc": "2026-03-15T08:11:01Z",
      "industry": "电气设备",
      "limit_type": "U",
      "close": "6.94",
      "up_limit": "6.94",
      "down_limit": "5.68",
      "fd_amount": "49132424.0",
      "first_time": "134355",
      "last_time": "144928",
      "题材加成": 0.7946272018253463,
      "板块": "电气设备"
    }
  ],
  "full": [
    {
      "rank": 1,
      "ts_code": "002445.SZ",
      "name": "中南文化",
      "board": "钢加工",
      "StrengthScore": 43.644068,
      "ThemeBoost": 0.0,
      "prob_rule": 0.531314270719221,
      "prob_ml": 0.6340905728744572,
      "prob_final": 0.6340905728744572,
      "Probability": 0.6340905728744572,
      "final_score": 0.5311515370121201,
      "score": 0.5311515370121201,
      "prob": 0.6340905728744572,
      "strength01": 0.43644067999999997,
      "theme01": 0.0,
      "trade_date": "20260313",
      "seal_amount": 487232888.0,
      "open_times": 0.0,
      "turnover_rate": 7.7207,
      "prob_src": "ml",
      "prob_ml_available": true,
      "prob_fusion_mode": "ml_first",
      "run_mode": "auto_daily",
      "run_time_utc": "2026-03-15T08:11:01Z",
      "industry": "钢加工",
      "limit_type": "U",
      "close": "4.49",
      "up_limit": "4.49",
      "down_limit": "3.67",
      "fd_amount": "487232888.0",
      "first_time": "92500",
      "last_time": "92500",
      "题材加成": 0.0,
      "板块": "钢加工"
    },
    {
      "rank": 2,
      "ts_code": "600722.SH",
      "name": "金牛化工",
      "board": "化工原料",
      "StrengthScore": 48.508475,
      "ThemeBoost": 1.0,
      "prob_rule": 0.5021977910684783,
      "prob_ml": 0.5039595290743865,
      "prob_final": 0.5039595290743865,
      "Probability": 0.5039595290743865,
      "final_score": 0.5267116972751476,
      "score": 0.5267116972751476,
      "prob": 0.5039595290743865,
      "strength01": 0.48508474999999995,
      "theme01": 0.7692307692307692,
      "trade_date": "20260313",
      "seal_amount": 25104402.0,
      "open_times": 19.0,
      "turnover_rate": 59.4514,
      "prob_src": "ml",
      "prob_ml_available": true,
      "prob_fusion_mode": "ml_first",
      "run_mode": "auto_daily",
      "run_time_utc": "2026-03-15T08:11:01Z",
      "industry": "化工原料",
      "limit_type": "U",
      "close": "16.94",
      "up_limit": "16.94",
      "down_limit": "13.86",
      "fd_amount": "25104402.0",
      "first_time": "94004",
      "last_time": "144849",
      "题材加成": 1.0,
      "板块": "化工原料"
    },
    {
      "rank": 3,
      "ts_code": "003027.SZ",
      "name": "同兴科技",
      "board": "环境保护",
      "StrengthScore": 52.254237,
      "ThemeBoost": 0.04865851676579642,
      "prob_rule": 0.6151064406701515,
      "prob_ml": 0.5344864266829616,
      "prob_final": 0.5344864266829616,
      "Probability": 0.5344864266829616,
      "final_score": 0.4823919355062114,
      "score": 0.4823919355062114,
      "prob": 0.5344864266829616,
      "strength01": 0.52254237,
      "theme01": 0.03742962828138186,
      "trade_date": "20260313",
      "seal_amount": 107000572.0,
      "open_times": 0.0,
      "turnover_rate": 13.8841,
      "prob_src": "ml",
      "prob_ml_available": true,
      "prob_fusion_mode": "ml_first",
      "run_mode": "auto_daily",
      "run_time_utc": "2026-03-15T08:11:01Z",
      "industry": "环境保护",
      "limit_type": "U",
      "close": "24.52",
      "up_limit": "24.52",
      "down_limit": "20.06",
      "fd_amount": "107000572.0",
      "first_time": "105245",
      "last_time": "105245",
      "题材加成": 0.04865851676579642,
      "板块": "环境保护"
    },
    {
      "rank": 4,
      "ts_code": "600307.SH",
      "name": "酒钢宏兴",
      "board": "普钢",
      "StrengthScore": 62.254237,
      "ThemeBoost": 0.08,
      "prob_rule": 0.601087505930745,
      "prob_ml": 0.3619317627362545,
      "prob_final": 0.3619317627362545,
      "Probability": 0.3619317627362545,
      "final_score": 0.38401455406922436,
      "score": 0.38401455406922436,
      "prob": 0.3619317627362545,
      "strength01": 0.62254237,
      "theme01": 0.061538461538461535,
      "trade_date": "20260313",
      "seal_amount": 51620394.0,
      "open_times": 4.0,
      "turnover_rate": 16.5461,
      "prob_src": "ml",
      "prob_ml_available": true,
      "prob_fusion_mode": "ml_first",
      "run_mode": "auto_daily",
      "run_time_utc": "2026-03-15T08:11:01Z",
      "industry": "普钢",
      "limit_type": "U",
      "close": "2.22",
      "up_limit": "2.22",
      "down_limit": "1.82",
      "fd_amount": "51620394.0",
      "first_time": "93459",
      "last_time": "131441",
      "题材加成": 0.08,
      "板块": "普钢"
    },
    {
      "rank": 5,
      "ts_code": "600691.SH",
      "name": "潞化科技",
      "board": "农药化肥",
      "StrengthScore": 76.728814,
      "ThemeBoost": 0.44012104274902347,
      "prob_rule": 0.7023956625543502,
      "prob_ml": 0.2524007518294422,
      "prob_final": 0.2524007518294422,
      "Probability": 0.2524007518294422,
      "final_score": 0.3639936191074576,
      "score": 0.3639936191074576,
      "prob": 0.2524007518294422,
      "strength01": 0.76728814,
      "theme01": 0.3385546482684796,
      "trade_date": "20260313",
      "seal_amount": 106234341.0,
      "open_times": 1.0,
      "turnover_rate": 5.9848,
      "prob_src": "ml",
      "prob_ml_available": true,
      "prob_fusion_mode": "ml_first",
      "run_mode": "auto_daily",
      "run_time_utc": "2026-03-15T08:11:01Z",
      "industry": "农药化肥",
      "limit_type": "U",
      "close": "4.43",
      "up_limit": "4.43",
      "down_limit": "3.63",
      "fd_amount": "106234341.0",
      "first_time": "92504",
      "last_time": "93022",
      "题材加成": 0.44012104274902347,
      "板块": "农药化肥"
    },
    {
      "rank": 6,
      "ts_code": "603929.SH",
      "name": "亚翔集成",
      "board": "装修装饰",
      "StrengthScore": 66.728814,
      "ThemeBoost": 0.0,
      "prob_rule": 0.5998609578269766,
      "prob_ml": 0.2965521413747995,
      "prob_final": 0.2965521413747995,
      "Probability": 0.2965521413747995,
      "final_score": 0.3410441269623597,
      "score": 0.3410441269623597,
      "prob": 0.2965521413747995,
      "strength01": 0.66728814,
      "theme01": 0.0,
      "trade_date": "20260313",
      "seal_amount": 219353146.0,
      "open_times": 0.0,
      "turnover_rate": 2.6811,
      "prob_src": "ml",
      "prob_ml_available": true,
      "prob_fusion_mode": "ml_first",
      "run_mode": "auto_daily",
      "run_time_utc": "2026-03-15T08:11:01Z",
      "industry": "装修装饰",
      "limit_type": "U",
      "close": "140.83",
      "up_limit": "140.83",
      "down_limit": "115.23",
      "fd_amount": "219353146.0",
      "first_time": "93000",
      "last_time": "93000",
      "题材加成": 0.0,
      "板块": "装修装饰"
    },
    {
      "rank": 7,
      "ts_code": "002109.SZ",
      "name": "兴化股份",
      "board": "化工原料",
      "StrengthScore": 67.067797,
      "ThemeBoost": 1.0,
      "prob_rule": 0.8021747448733817,
      "prob_ml": 0.15987259568054218,
      "prob_final": 0.15987259568054218,
      "Probability": 0.15987259568054218,
      "final_score": 0.3229694878994565,
      "score": 0.3229694878994565,
      "prob": 0.15987259568054218,
      "strength01": 0.67067797,
      "theme01": 0.7692307692307692,
      "trade_date": "20260313",
      "seal_amount": 33441422.0,
      "open_times": 1.0,
      "turnover_rate": 17.175,
      "prob_src": "ml",
      "prob_ml_available": true,
      "prob_fusion_mode": "ml_first",
      "run_mode": "auto_daily",
      "run_time_utc": "2026-03-15T08:11:01Z",
      "industry": "化工原料",
      "limit_type": "U",
      "close": "5.18",
      "up_limit": "5.18",
      "down_limit": "4.24",
      "fd_amount": "33441422.0",
      "first_time": "93200",
      "last_time": "100521",
      "题材加成": 1.0,
      "板块": "化工原料"
    },
    {
      "rank": 8,
      "ts_code": "600121.SH",
      "name": "郑州煤电",
      "board": "煤炭开采",
      "StrengthScore": 65.40678,
      "ThemeBoost": 0.08,
      "prob_rule": 0.6650702421147496,
      "prob_ml": 0.25847997947970686,
      "prob_final": 0.25847997947970686,
      "Probability": 0.25847997947970686,
      "final_score": 0.317903391789641,
      "score": 0.317903391789641,
      "prob": 0.25847997947970686,
      "strength01": 0.6540678,
      "theme01": 0.061538461538461535,
      "trade_date": "20260313",
      "seal_amount": 170038778.0,
      "open_times": 0.0,
      "turnover_rate": 12.2185,
      "prob_src": "ml",
      "prob_ml_available": true,
      "prob_fusion_mode": "ml_first",
      "run_mode": "auto_daily",
      "run_time_utc": "2026-03-15T08:11:01Z",
      "industry": "煤炭开采",
      "limit_type": "U",
      "close": "5.65",
      "up_limit": "5.65",
      "down_limit": "4.63",
      "fd_amount": "170038778.0",
      "first_time": "92500",
      "last_time": "92500",
      "题材加成": 0.08,
      "板块": "煤炭开采"
    },
    {
      "rank": 9,
      "ts_code": "603538.SH",
      "name": "美诺华",
      "board": "化学制药",
      "StrengthScore": 46.932203,
      "ThemeBoost": 0.0,
      "prob_rule": 0.5880845140770732,
      "prob_ml": 0.25435671439910934,
      "prob_final": 0.25435671439910934,
      "Probability": 0.25435671439910934,
      "final_score": 0.2719141060793766,
      "score": 0.2719141060793766,
      "prob": 0.25435671439910934,
      "strength01": 0.46932203,
      "theme01": 0.0,
      "trade_date": "20260313",
      "seal_amount": 112124186.0,
      "open_times": 0.0,
      "turnover_rate": 14.3082,
      "prob_src": "ml",
      "prob_ml_available": true,
      "prob_fusion_mode": "ml_first",
      "run_mode": "auto_daily",
      "run_time_utc": "2026-03-15T08:11:01Z",
      "industry": "化学制药",
      "limit_type": "U",
      "close": "25.37",
      "up_limit": "25.37",
      "down_limit": "20.75",
      "fd_amount": "112124186.0",
      "first_time": "112950",
      "last_time": "112950",
      "题材加成": 0.0,
      "板块": "化学制药"
    },
    {
      "rank": 10,
      "ts_code": "601218.SH",
      "name": "吉鑫科技",
      "board": "电气设备",
      "StrengthScore": 50.118644,
      "ThemeBoost": 0.7946272018253463,
      "prob_rule": 0.6128322643257663,
      "prob_ml": 0.1392663227431279,
      "prob_final": 0.1392663227431279,
      "Probability": 0.1392663227431279,
      "final_score": 0.25884888329137007,
      "score": 0.25884888329137007,
      "prob": 0.1392663227431279,
      "strength01": 0.50118644,
      "theme01": 0.6112516937118049,
      "trade_date": "20260313",
      "seal_amount": 49132424.0,
      "open_times": 2.0,
      "turnover_rate": 31.6714,
      "prob_src": "ml",
      "prob_ml_available": true,
      "prob_fusion_mode": "ml_first",
      "run_mode": "auto_daily",
      "run_time_utc": "2026-03-15T08:11:01Z",
      "industry": "电气设备",
      "limit_type": "U",
      "close": "6.94",
      "up_limit": "6.94",
      "down_limit": "5.68",
      "fd_amount": "49132424.0",
      "first_time": "134355",
      "last_time": "144928",
      "题材加成": 0.7946272018253463,
      "板块": "电气设备"
    },
    {
      "rank": 11,
      "ts_code": "603169.SH",
      "name": "兰石重装",
      "board": "专用机械",
      "StrengthScore": 47.915254,
      "ThemeBoost": 0.0,
      "prob_rule": 0.5978606756170162,
      "prob_ml": 0.23050074662438727,
      "prob_final": 0.23050074662438727,
      "Probability": 0.23050074662438727,
      "final_score": 0.2571810306370711,
      "score": 0.2571810306370711,
      "prob": 0.23050074662438727,
      "strength01": 0.47915253999999996,
      "theme01": 0.0,
      "trade_date": "20260313",
      "seal_amount": 159380480.0,
      "open_times": 0.0,
      "turnover_rate": 15.7737,
      "prob_src": "ml",
      "prob_ml_available": true,
      "prob_fusion_mode": "ml_first",
      "run_mode": "auto_daily",
      "run_time_utc": "2026-03-15T08:11:01Z",
      "industry": "专用机械",
      "limit_type": "U",
      "close": "12.8",
      "up_limit": "12.8",
      "down_limit": "10.48",
      "fd_amount": "159380480.0",
      "first_time": "104350",
      "last_time": "104350",
      "题材加成": 0.0,
      "板块": "专用机械"
    },
    {
      "rank": 12,
      "ts_code": "300981.SZ",
      "name": "中红医疗",
      "board": "医疗保健",
      "StrengthScore": 34.322034,
      "ThemeBoost": 0.3401553699246989,
      "prob_rule": 0.5001678802707556,
      "prob_ml": 0.22810869506285278,
      "prob_final": 0.22810869506285278,
      "Probability": 0.22810869506285278,
      "final_score": 0.2544859522305123,
      "score": 0.2544859522305123,
      "prob": 0.22810869506285278,
      "strength01": 0.34322034,
      "theme01": 0.261657976865153,
      "trade_date": "20260313",
      "seal_amount": 54087409.0,
      "open_times": 0.0,
      "turnover_rate": 36.6569,
      "prob_src": "ml",
      "prob_ml_available": true,
      "prob_fusion_mode": "ml_first",
      "run_mode": "auto_daily",
      "run_time_utc": "2026-03-15T08:11:01Z",
      "industry": "医疗保健",
      "limit_type": "U",
      "close": "15.77",
      "up_limit": "15.77",
      "down_limit": "10.51",
      "fd_amount": "54087409.0",
      "first_time": "140030",
      "last_time": "140030",
      "题材加成": 0.3401553699246989,
      "板块": "医疗保健"
    },
    {
      "rank": 13,
      "ts_code": "601611.SH",
      "name": "中国核建",
      "board": "建筑工程",
      "StrengthScore": 34.949153,
      "ThemeBoost": 0.479801681970459,
      "prob_rule": 0.49354799757817847,
      "prob_ml": 0.20626047824642385,
      "prob_final": 0.20626047824642385,
      "Probability": 0.20626047824642385,
      "final_score": 0.251188462462532,
      "score": 0.251188462462532,
      "prob": 0.20626047824642385,
      "strength01": 0.34949153000000005,
      "theme01": 0.3690782169003531,
      "trade_date": "20260313",
      "seal_amount": 106137997.0,
      "open_times": 3.0,
      "turnover_rate": 30.665,
      "prob_src": "ml",
      "prob_ml_available": true,
      "prob_fusion_mode": "ml_first",
      "run_mode": "auto_daily",
      "run_time_utc": "2026-03-15T08:11:01Z",
      "industry": "建筑工程",
      "limit_type": "U",
      "close": "19.21",
      "up_limit": "19.21",
      "down_limit": "15.71",
      "fd_amount": "106137997.0",
      "first_time": "132032",
      "last_time": "140956",
      "题材加成": 0.479801681970459,
      "板块": "建筑工程"
    },
    {
      "rank": 14,
      "ts_code": "002669.SZ",
      "name": "康达新材",
      "board": "化工原料",
      "StrengthScore": 46.661017,
      "ThemeBoost": 1.0,
      "prob_rule": 0.7293805096259927,
      "prob_ml": 0.1084763870988036,
      "prob_final": 0.1084763870988036,
      "Probability": 0.1084763870988036,
      "final_score": 0.24617858189223946,
      "score": 0.24617858189223946,
      "prob": 0.1084763870988036,
      "strength01": 0.46661017,
      "theme01": 0.7692307692307692,
      "trade_date": "20260313",
      "seal_amount": 56168750.0,
      "open_times": 0.0,
      "turnover_rate": 15.2663,
      "prob_src": "ml",
      "prob_ml_available": true,
      "prob_fusion_mode": "ml_first",
      "run_mode": "auto_daily",
      "run_time_utc": "2026-03-15T08:11:01Z",
      "industry": "化工原料",
      "limit_type": "U",
      "close": "15.35",
      "up_limit": "15.35",
      "down_limit": "12.56",
      "fd_amount": "56168750.0",
      "first_time": "144730",
      "last_time": "144730",
      "题材加成": 1.0,
      "板块": "化工原料"
    },
    {
      "rank": 15,
      "ts_code": "002470.SZ",
      "name": "金正大",
      "board": "农药化肥",
      "StrengthScore": 55.305085,
      "ThemeBoost": 0.36012104274902346,
      "prob_rule": 0.6779131114977851,
      "prob_ml": 0.14542741601109715,
      "prob_final": 0.14542741601109715,
      "Probability": 0.14542741601109715,
      "final_score": 0.24011097988076985,
      "score": 0.24011097988076985,
      "prob": 0.14542741601109715,
      "strength01": 0.55305085,
      "theme01": 0.27701618673001804,
      "trade_date": "20260313",
      "seal_amount": 180192810.0,
      "open_times": 0.0,
      "turnover_rate": 15.5049,
      "prob_src": "ml",
      "prob_ml_available": true,
      "prob_fusion_mode": "ml_first",
      "run_mode": "auto_daily",
      "run_time_utc": "2026-03-15T08:11:01Z",
      "industry": "农药化肥",
      "limit_type": "U",
      "close": "3.22",
      "up_limit": "3.22",
      "down_limit": "2.64",
      "fd_amount": "180192810.0",
      "first_time": "93136",
      "last_time": "93136",
      "题材加成": 0.36012104274902346,
      "板块": "农药化肥"
    },
    {
      "rank": 16,
      "ts_code": "000010.SZ",
      "name": "美丽生态",
      "board": "建筑工程",
      "StrengthScore": 77.915254,
      "ThemeBoost": 0.479801681970459,
      "prob_rule": 0.7350384682771086,
      "prob_ml": 0.050733451677051955,
      "prob_final": 0.050733451677051955,
      "Probability": 0.050733451677051955,
      "final_score": 0.22825174586397173,
      "score": 0.22825174586397173,
      "prob": 0.050733451677051955,
      "strength01": 0.77915254,
      "theme01": 0.3690782169003531,
      "trade_date": "20260313",
      "seal_amount": 67120896.0,
      "open_times": 0.0,
      "turnover_rate": 6.7248,
      "prob_src": "ml",
      "prob_ml_available": true,
      "prob_fusion_mode": "ml_first",
      "run_mode": "auto_daily",
      "run_time_utc": "2026-03-15T08:11:01Z",
      "industry": "建筑工程",
      "limit_type": "U",
      "close": "4.53",
      "up_limit": "4.53",
      "down_limit": "3.71",
      "fd_amount": "67120896.0",
      "first_time": "93533",
      "last_time": "93533",
      "题材加成": 0.479801681970459,
      "板块": "建筑工程"
    },
    {
      "rank": 17,
      "ts_code": "002931.SZ",
      "name": "锋龙股份",
      "board": "机械基件",
      "StrengthScore": 54.932203,
      "ThemeBoost": 0.1766570212508551,
      "prob_rule": 0.6028505308154278,
      "prob_ml": 0.14221397108505973,
      "prob_final": 0.14221397108505973,
      "Probability": 0.14221397108505973,
      "final_score": 0.223003187394223,
      "score": 0.223003187394223,
      "prob": 0.14221397108505973,
      "strength01": 0.54932203,
      "theme01": 0.1358900163468116,
      "trade_date": "20260313",
      "seal_amount": 291847881.0,
      "open_times": 0.0,
      "turnover_rate": 7.6719,
      "prob_src": "ml",
      "prob_ml_available": true,
      "prob_fusion_mode": "ml_first",
      "run_mode": "auto_daily",
      "run_time_utc": "2026-03-15T08:11:01Z",
      "industry": "机械基件",
      "limit_type": "U",
      "close": "81.58",
      "up_limit": "81.58",
      "down_limit": "66.74",
      "fd_amount": "291847881.0",
      "first_time": "93018",
      "last_time": "93018",
      "题材加成": 0.1766570212508551,
      "板块": "机械基件"
    },
    {
      "rank": 18,
      "ts_code": "600746.SH",
      "name": "江苏索普",
      "board": "化工原料",
      "StrengthScore": 67.779661,
      "ThemeBoost": 1.0,
      "prob_rule": 0.805620490882178,
      "prob_ml": 0.01502952910179169,
      "prob_final": 0.01502952910179169,
      "Probability": 0.01502952910179169,
      "final_score": 0.22300306929433114,
      "score": 0.22300306929433114,
      "prob": 0.01502952910179169,
      "strength01": 0.67779661,
      "theme01": 0.7692307692307692,
      "trade_date": "20260313",
      "seal_amount": 15322522.0,
      "open_times": 1.0,
      "turnover_rate": 18.15,
      "prob_src": "ml",
      "prob_ml_available": true,
      "prob_fusion_mode": "ml_first",
      "run_mode": "auto_daily",
      "run_time_utc": "2026-03-15T08:11:01Z",
      "industry": "化工原料",
      "limit_type": "U",
      "close": "9.26",
      "up_limit": "9.26",
      "down_limit": "7.58",
      "fd_amount": "15322522.0",
      "first_time": "132622",
      "last_time": "135507",
      "题材加成": 1.0,
      "板块": "化工原料"
    },
    {
      "rank": 19,
      "ts_code": "000677.SZ",
      "name": "恒天海龙",
      "board": "化纤",
      "StrengthScore": 63.20339,
      "ThemeBoost": 0.0,
      "prob_rule": 0.5891650248444144,
      "prob_ml": 0.1320202668747846,
      "prob_final": 0.1320202668747846,
      "Probability": 0.1320202668747846,
      "final_score": 0.21882096681234925,
      "score": 0.21882096681234925,
      "prob": 0.1320202668747846,
      "strength01": 0.6320339,
      "theme01": 0.0,
      "trade_date": "20260313",
      "seal_amount": 117815253.0,
      "open_times": 0.0,
      "turnover_rate": 3.6038,
      "prob_src": "ml",
      "prob_ml_available": true,
      "prob_fusion_mode": "ml_first",
      "run_mode": "auto_daily",
      "run_time_utc": "2026-03-15T08:11:01Z",
      "industry": "化纤",
      "limit_type": "U",
      "close": "5.02",
      "up_limit": "5.02",
      "down_limit": "4.1",
      "fd_amount": "117815253.0",
      "first_time": "92500",
      "last_time": "92500",
      "题材加成": 0.0,
      "板块": "化纤"
    },
    {
      "rank": 20,
      "ts_code": "000890.SZ",
      "name": "法尔胜",
      "board": "环境保护",
      "StrengthScore": 59.067797,
      "ThemeBoost": 0.12865851676579643,
      "prob_rule": 0.626968334064458,
      "prob_ml": 0.12349295641928366,
      "prob_final": 0.12349295641928366,
      "Probability": 0.12349295641928366,
      "final_score": 0.21447747247548293,
      "score": 0.21447747247548293,
      "prob": 0.12349295641928366,
      "strength01": 0.59067797,
      "theme01": 0.0989680898198434,
      "trade_date": "20260313",
      "seal_amount": 55731929.0,
      "open_times": 2.0,
      "turnover_rate": 15.597,
      "prob_src": "ml",
      "prob_ml_available": true,
      "prob_fusion_mode": "ml_first",
      "run_mode": "auto_daily",
      "run_time_utc": "2026-03-15T08:11:01Z",
      "industry": "环境保护",
      "limit_type": "U",
      "close": "11.09",
      "up_limit": "11.09",
      "down_limit": "9.07",
      "fd_amount": "55731929.0",
      "first_time": "93142",
      "last_time": "93315",
      "题材加成": 0.12865851676579643,
      "板块": "环境保护"
    },
    {
      "rank": 21,
      "ts_code": "600227.SH",
      "name": "赤天化",
      "board": "农药化肥",
      "StrengthScore": 41.559322,
      "ThemeBoost": 0.44012104274902347,
      "prob_rule": 0.48969650534912146,
      "prob_ml": 0.13611727800131798,
      "prob_final": 0.13611727800131798,
      "Probability": 0.13611727800131798,
      "final_score": 0.21225620342777057,
      "score": 0.21225620342777057,
      "prob": 0.13611727800131798,
      "strength01": 0.41559322000000004,
      "theme01": 0.3385546482684796,
      "trade_date": "20260313",
      "seal_amount": 28400166.0,
      "open_times": 3.0,
      "turnover_rate": 37.7251,
      "prob_src": "ml",
      "prob_ml_available": true,
      "prob_fusion_mode": "ml_first",
      "run_mode": "auto_daily",
      "run_time_utc": "2026-03-15T08:11:01Z",
      "industry": "农药化肥",
      "limit_type": "U",
      "close": "4.37",
      "up_limit": "4.37",
      "down_limit": "3.57",
      "fd_amount": "28400166.0",
      "first_time": "94035",
      "last_time": "144914",
      "题材加成": 0.44012104274902347,
      "板块": "农药化肥"
    },
    {
      "rank": 22,
      "ts_code": "600234.SH",
      "name": "科新发展",
      "board": "装修装饰",
      "StrengthScore": 63.508475,
      "ThemeBoost": 0.0,
      "prob_rule": 0.6005058317728647,
      "prob_ml": 0.12102967498645587,
      "prob_final": 0.12102967498645587,
      "Probability": 0.12102967498645587,
      "final_score": 0.21173772249051914,
      "score": 0.21173772249051914,
      "prob": 0.12102967498645587,
      "strength01": 0.63508475,
      "theme01": 0.0,
      "trade_date": "20260313",
      "seal_amount": 73641867.0,
      "open_times": 0.0,
      "turnover_rate": 5.497,
      "prob_src": "ml",
      "prob_ml_available": true,
      "prob_fusion_mode": "ml_first",
      "run_mode": "auto_daily",
      "run_time_utc": "2026-03-15T08:11:01Z",
      "industry": "装修装饰",
      "limit_type": "U",
      "close": "14.92",
      "up_limit": "14.92",
      "down_limit": "12.2",
      "fd_amount": "73641867.0",
      "first_time": "132232",
      "last_time": "132232",
      "题材加成": 0.0,
      "板块": "装修装饰"
    },
    {
      "rank": 23,
      "ts_code": "002637.SZ",
      "name": "赞宇科技",
      "board": "日用化工",
      "StrengthScore": 70.694915,
      "ThemeBoost": 0.0,
      "prob_rule": 0.6371631967540934,
      "prob_ml": 0.08898759433745294,
      "prob_final": 0.08898759433745294,
      "Probability": 0.08898759433745294,
      "final_score": 0.2036811460362171,
      "score": 0.2036811460362171,
      "prob": 0.08898759433745294,
      "strength01": 0.7069491499999999,
      "theme01": 0.0,
      "trade_date": "20260313",
      "seal_amount": 107489097.0,
      "open_times": 0.0,
      "turnover_rate": 6.5515,
      "prob_src": "ml",
      "prob_ml_available": true,
      "prob_fusion_mode": "ml_first",
      "run_mode": "auto_daily",
      "run_time_utc": "2026-03-15T08:11:01Z",
      "industry": "日用化工",
      "limit_type": "U",
      "close": "15.87",
      "up_limit": "15.87",
      "down_limit": "12.99",
      "fd_amount": "107489097.0",
      "first_time": "130554",
      "last_time": "130554",
      "题材加成": 0.0,
      "板块": "日用化工"
    },
    {
      "rank": 24,
      "ts_code": "605222.SH",
      "name": "起帆电缆",
      "board": "电气设备",
      "StrengthScore": 58.016949,
      "ThemeBoost": 0.7946272018253463,
      "prob_rule": 0.7380190440112939,
      "prob_ml": 0.03407618990366274,
      "prob_final": 0.03407618990366274,
      "Probability": 0.03407618990366274,
      "final_score": 0.20101240030374445,
      "score": 0.20101240030374445,
      "prob": 0.03407618990366274,
      "strength01": 0.58016949,
      "theme01": 0.6112516937118049,
      "trade_date": "20260313",
      "seal_amount": 24771052.0,
      "open_times": 0.0,
      "turnover_rate": 13.0447,
      "prob_src": "ml",
      "prob_ml_available": true,
      "prob_fusion_mode": "ml_first",
      "run_mode": "auto_daily",
      "run_time_utc": "2026-03-15T08:11:01Z",
      "industry": "电气设备",
      "limit_type": "U",
      "close": "23.06",
      "up_limit": "23.06",
      "down_limit": "18.86",
      "fd_amount": "24771052.0",
      "first_time": "130826",
      "last_time": "130826",
      "题材加成": 0.7946272018253463,
      "板块": "电气设备"
    },
    {
      "rank": 25,
      "ts_code": "002323.SZ",
      "name": "雅博股份",
      "board": "建筑工程",
      "StrengthScore": 57.542373,
      "ThemeBoost": 0.479801681970459,
      "prob_rule": 0.6945024566296023,
      "prob_ml": 0.06864058472024508,
      "prob_final": 0.06864058472024508,
      "Probability": 0.06864058472024508,
      "final_score": 0.2000409769942069,
      "score": 0.2000409769942069,
      "prob": 0.06864058472024508,
      "strength01": 0.57542373,
      "theme01": 0.3690782169003531,
      "trade_date": "20260313",
      "seal_amount": 39853278.0,
      "open_times": 0.0,
      "turnover_rate": 22.5898,
      "prob_src": "ml",
      "prob_ml_available": true,
      "prob_fusion_mode": "ml_first",
      "run_mode": "auto_daily",
      "run_time_utc": "2026-03-15T08:11:01Z",
      "industry": "建筑工程",
      "limit_type": "U",
      "close": "2.54",
      "up_limit": "2.54",
      "down_limit": "2.08",
      "fd_amount": "39853278.0",
      "first_time": "110642",
      "last_time": "110642",
      "题材加成": 0.479801681970459,
      "板块": "建筑工程"
    },
    {
      "rank": 26,
      "ts_code": "002543.SZ",
      "name": "万和电气",
      "board": "家用电器",
      "StrengthScore": 71.627119,
      "ThemeBoost": 0.6230854212758787,
      "prob_rule": 0.6952273177108681,
      "prob_ml": 0.011682338684109037,
      "prob_final": 0.011682338684109037,
      "Probability": 0.011682338684109037,
      "final_score": 0.19936152286932857,
      "score": 0.19936152286932857,
      "prob": 0.011682338684109037,
      "strength01": 0.71627119,
      "theme01": 0.47929647790452207,
      "trade_date": "20260313",
      "seal_amount": 17124002.0,
      "open_times": 3.0,
      "turnover_rate": 9.5101,
      "prob_src": "ml",
      "prob_ml_available": true,
      "prob_fusion_mode": "ml_first",
      "run_mode": "auto_daily",
      "run_time_utc": "2026-03-15T08:11:01Z",
      "industry": "家用电器",
      "limit_type": "U",
      "close": "9.79",
      "up_limit": "9.79",
      "down_limit": "8.01",
      "fd_amount": "17124002.0",
      "first_time": "103109",
      "last_time": "104224",
      "题材加成": 0.6230854212758787,
      "板块": "家用电器"
    },
    {
      "rank": 27,
      "ts_code": "600847.SH",
      "name": "万里股份",
      "board": "电气设备",
      "StrengthScore": 65.135593,
      "ThemeBoost": 0.7946272018253463,
      "prob_rule": 0.7409207596521418,
      "prob_ml": 0.008981976250553676,
      "prob_final": 0.008981976250553676,
      "Probability": 0.008981976250553676,
      "final_score": 0.1976837387465681,
      "score": 0.1976837387465681,
      "prob": 0.008981976250553676,
      "strength01": 0.65135593,
      "theme01": 0.6112516937118049,
      "trade_date": "20260313",
      "seal_amount": 81478683.0,
      "open_times": 0.0,
      "turnover_rate": 9.0488,
      "prob_src": "ml",
      "prob_ml_available": true,
      "prob_fusion_mode": "ml_first",
      "run_mode": "auto_daily",
      "run_time_utc": "2026-03-15T08:11:01Z",
      "industry": "电气设备",
      "limit_type": "U",
      "close": "15.51",
      "up_limit": "15.51",
      "down_limit": "12.69",
      "fd_amount": "81478683.0",
      "first_time": "112140",
      "last_time": "112140",
      "题材加成": 0.7946272018253463,
      "板块": "电气设备"
    },
    {
      "rank": 28,
      "ts_code": "603659.SH",
      "name": "璞泰来",
      "board": "化工原料",
      "StrengthScore": 51.847458,
      "ThemeBoost": 1.0,
      "prob_rule": 0.6979075329989045,
      "prob_ml": 0.02020897591989254,
      "prob_final": 0.02020897591989254,
      "Probability": 0.02020897591989254,
      "final_score": 0.19476427606700175,
      "score": 0.19476427606700175,
      "prob": 0.02020897591989254,
      "strength01": 0.51847458,
      "theme01": 0.7692307692307692,
      "trade_date": "20260313",
      "seal_amount": 88180188.0,
      "open_times": 0.0,
      "turnover_rate": 6.7751,
      "prob_src": "ml",
      "prob_ml_available": true,
      "prob_fusion_mode": "ml_first",
      "run_mode": "auto_daily",
      "run_time_utc": "2026-03-15T08:11:01Z",
      "industry": "化工原料",
      "limit_type": "U",
      "close": "32.41",
      "up_limit": "32.41",
      "down_limit": "26.51",
      "fd_amount": "88180188.0",
      "first_time": "94917",
      "last_time": "94917",
      "题材加成": 1.0,
      "板块": "化工原料"
    },
    {
      "rank": 29,
      "ts_code": "002487.SZ",
      "name": "大金重工",
      "board": "电气设备",
      "StrengthScore": 44.525424,
      "ThemeBoost": 0.8746272018253463,
      "prob_rule": 0.6586492690598592,
      "prob_ml": 0.05465172010193483,
      "prob_final": 0.05465172010193483,
      "Probability": 0.05465172010193483,
      "final_score": 0.19458606759638103,
      "score": 0.19458606759638103,
      "prob": 0.05465172010193483,
      "strength01": 0.44525424,
      "theme01": 0.6727901552502663,
      "trade_date": "20260313",
      "seal_amount": 210266728.0,
      "open_times": 2.0,
      "turnover_rate": 13.2576,
      "prob_src": "ml",
      "prob_ml_available": true,
      "prob_fusion_mode": "ml_first",
      "run_mode": "auto_daily",
      "run_time_utc": "2026-03-15T08:11:01Z",
      "industry": "电气设备",
      "limit_type": "U",
      "close": "80.65",
      "up_limit": "80.65",
      "down_limit": "65.99",
      "fd_amount": "210266728.0",
      "first_time": "132430",
      "last_time": "132718",
      "题材加成": 0.8746272018253463,
      "板块": "电气设备"
    },
    {
      "rank": 30,
      "ts_code": "600336.SH",
      "name": "澳柯玛",
      "board": "家用电器",
      "StrengthScore": 70.084746,
      "ThemeBoost": 0.6230854212758787,
      "prob_rule": 0.7322609506950879,
      "prob_ml": 0.006388963473449866,
      "prob_final": 0.006388963473449866,
      "Probability": 0.006388963473449866,
      "final_score": 0.19257141422186716,
      "score": 0.19257141422186716,
      "prob": 0.006388963473449866,
      "strength01": 0.70084746,
      "theme01": 0.47929647790452207,
      "trade_date": "20260313",
      "seal_amount": 24157994.0,
      "open_times": 1.0,
      "turnover_rate": 10.709,
      "prob_src": "ml",
      "prob_ml_available": true,
      "prob_fusion_mode": "ml_first",
      "run_mode": "auto_daily",
      "run_time_utc": "2026-03-15T08:11:01Z",
      "industry": "家用电器",
      "limit_type": "U",
      "close": "8.18",
      "up_limit": "8.18",
      "down_limit": "6.7",
      "fd_amount": "24157994.0",
      "first_time": "130704",
      "last_time": "131543",
      "题材加成": 0.6230854212758787,
      "板块": "家用电器"
    },
    {
      "rank": 31,
      "ts_code": "002165.SZ",
      "name": "红 宝 丽",
      "board": "化工原料",
      "StrengthScore": 37.915254,
      "ThemeBoost": 1.0,
      "prob_rule": 0.6194923856898579,
      "prob_ml": 0.05321721883174327,
      "prob_final": 0.05321721883174327,
      "Probability": 0.05321721883174327,
      "final_score": 0.19000563810529722,
      "score": 0.19000563810529722,
      "prob": 0.05321721883174327,
      "strength01": 0.37915254,
      "theme01": 0.7692307692307692,
      "trade_date": "20260313",
      "seal_amount": 158778039.0,
      "open_times": 0.0,
      "turnover_rate": 32.8134,
      "prob_src": "ml",
      "prob_ml_available": true,
      "prob_fusion_mode": "ml_first",
      "run_mode": "auto_daily",
      "run_time_utc": "2026-03-15T08:11:01Z",
      "industry": "化工原料",
      "limit_type": "U",
      "close": "12.76",
      "up_limit": "12.76",
      "down_limit": "10.44",
      "fd_amount": "158778039.0",
      "first_time": "94300",
      "last_time": "94300",
      "题材加成": 1.0,
      "板块": "化工原料"
    },
    {
      "rank": 32,
      "ts_code": "002084.SZ",
      "name": "海鸥住工",
      "board": "家居用品",
      "StrengthScore": 62.559322,
      "ThemeBoost": 0.0,
      "prob_rule": 0.6567790170561045,
      "prob_ml": 0.09246477514780398,
      "prob_final": 0.09246477514780398,
      "Probability": 0.09246477514780398,
      "final_score": 0.1898439866034628,
      "score": 0.1898439866034628,
      "prob": 0.09246477514780398,
      "strength01": 0.6255932200000001,
      "theme01": 0.0,
      "trade_date": "20260313",
      "seal_amount": 20735792.0,
      "open_times": 0.0,
      "turnover_rate": 15.0227,
      "prob_src": "ml",
      "prob_ml_available": true,
      "prob_fusion_mode": "ml_first",
      "run_mode": "auto_daily",
      "run_time_utc": "2026-03-15T08:11:01Z",
      "industry": "家居用品",
      "limit_type": "U",
      "close": "4.29",
      "up_limit": "4.29",
      "down_limit": "3.51",
      "fd_amount": "20735792.0",
      "first_time": "112830",
      "last_time": "112830",
      "题材加成": 0.0,
      "板块": "家居用品"
    },
    {
      "rank": 33,
      "ts_code": "601669.SH",
      "name": "中国电建",
      "board": "建筑工程",
      "StrengthScore": 44.050847,
      "ThemeBoost": 0.479801681970459,
      "prob_rule": 0.6220980484333338,
      "prob_ml": 0.09243358009546132,
      "prob_final": 0.09243358009546132,
      "Probability": 0.09243358009546132,
      "final_score": 0.18971302175685825,
      "score": 0.18971302175685825,
      "prob": 0.09243358009546132,
      "strength01": 0.44050847,
      "theme01": 0.3690782169003531,
      "trade_date": "20260313",
      "seal_amount": 681678306.0,
      "open_times": 1.0,
      "turnover_rate": 22.2617,
      "prob_src": "ml",
      "prob_ml_available": true,
      "prob_fusion_mode": "ml_first",
      "run_mode": "auto_daily",
      "run_time_utc": "2026-03-15T08:11:01Z",
      "industry": "建筑工程",
      "limit_type": "U",
      "close": "7.19",
      "up_limit": "7.19",
      "down_limit": "5.89",
      "fd_amount": "681678306.0",
      "first_time": "93456",
      "last_time": "101453",
      "题材加成": 0.479801681970459,
      "板块": "建筑工程"
    },
    {
      "rank": 34,
      "ts_code": "002438.SZ",
      "name": "江苏神通",
      "board": "机械基件",
      "StrengthScore": 57.237288,
      "ThemeBoost": 0.1766570212508551,
      "prob_rule": 0.6168356931671872,
      "prob_ml": 0.08678392076816653,
      "prob_final": 0.08678392076816653,
      "Probability": 0.08678392076816653,
      "final_score": 0.18881232217239777,
      "score": 0.18881232217239777,
      "prob": 0.08678392076816653,
      "strength01": 0.57237288,
      "theme01": 0.1358900163468116,
      "trade_date": "20260313",
      "seal_amount": 106285077.0,
      "open_times": 0.0,
      "turnover_rate": 8.2931,
      "prob_src": "ml",
      "prob_ml_available": true,
      "prob_fusion_mode": "ml_first",
      "run_mode": "auto_daily",
      "run_time_utc": "2026-03-15T08:11:01Z",
      "industry": "机械基件",
      "limit_type": "U",
      "close": "19.26",
      "up_limit": "19.26",
      "down_limit": "15.76",
      "fd_amount": "106285077.0",
      "first_time": "133512",
      "last_time": "133512",
      "题材加成": 0.1766570212508551,
      "板块": "机械基件"
    },
    {
      "rank": 35,
      "ts_code": "001366.SZ",
      "name": "播恩集团",
      "board": "饲料",
      "StrengthScore": 76.389831,
      "ThemeBoost": 0.0,
      "prob_rule": 0.6896487581190374,
      "prob_ml": 0.050217065591160424,
      "prob_final": 0.050217065591160424,
      "Probability": 0.050217065591160424,
      "final_score": 0.1879316079138123,
      "score": 0.1879316079138123,
      "prob": 0.050217065591160424,
      "strength01": 0.76389831,
      "theme01": 0.0,
      "trade_date": "20260313",
      "seal_amount": 43056320.0,
      "open_times": 0.0,
      "turnover_rate": 10.6633,
      "prob_src": "ml",
      "prob_ml_available": true,
      "prob_fusion_mode": "ml_first",
      "run_mode": "auto_daily",
      "run_time_utc": "2026-03-15T08:11:01Z",
      "industry": "饲料",
      "limit_type": "U",
      "close": "15.76",
      "up_limit": "15.76",
      "down_limit": "12.9",
      "fd_amount": "43056320.0",
      "first_time": "100348",
      "last_time": "100348",
      "题材加成": 0.0,
      "板块": "饲料"
    },
    {
      "rank": 36,
      "ts_code": "002056.SZ",
      "name": "横店东磁",
      "board": "电气设备",
      "StrengthScore": 55.355932,
      "ThemeBoost": 0.8746272018253463,
      "prob_rule": 0.6696068830590496,
      "prob_ml": 0.013071021757220604,
      "prob_final": 0.013071021757220604,
      "Probability": 0.013071021757220604,
      "final_score": 0.1871405947550811,
      "score": 0.1871405947550811,
      "prob": 0.013071021757220604,
      "strength01": 0.5535593200000001,
      "theme01": 0.6727901552502663,
      "trade_date": "20260313",
      "seal_amount": 42809128.0,
      "open_times": 3.0,
      "turnover_rate": 10.6203,
      "prob_src": "ml",
      "prob_ml_available": true,
      "prob_fusion_mode": "ml_first",
      "run_mode": "auto_daily",
      "run_time_utc": "2026-03-15T08:11:01Z",
      "industry": "电气设备",
      "limit_type": "U",
      "close": "25.84",
      "up_limit": "25.84",
      "down_limit": "21.14",
      "fd_amount": "42809128.0",
      "first_time": "100351",
      "last_time": "145424",
      "题材加成": 0.8746272018253463,
      "板块": "电气设备"
    },
    {
      "rank": 37,
      "ts_code": "603029.SH",
      "name": "天鹅股份",
      "board": "农用机械",
      "StrengthScore": 63.440678,
      "ThemeBoost": 0.0,
      "prob_rule": 0.6519736378097925,
      "prob_ml": 0.07014521990813936,
      "prob_final": 0.07014521990813936,
      "Probability": 0.07014521990813936,
      "final_score": 0.17598300993569754,
      "score": 0.17598300993569754,
      "prob": 0.07014521990813936,
      "strength01": 0.63440678,
      "theme01": 0.0,
      "trade_date": "20260313",
      "seal_amount": 96608808.0,
      "open_times": 0.0,
      "turnover_rate": 13.2545,
      "prob_src": "ml",
      "prob_ml_available": true,
      "prob_fusion_mode": "ml_first",
      "run_mode": "auto_daily",
      "run_time_utc": "2026-03-15T08:11:01Z",
      "industry": "农用机械",
      "limit_type": "U",
      "close": "21.6",
      "up_limit": "21.6",
      "down_limit": "17.68",
      "fd_amount": "96608808.0",
      "first_time": "104716",
      "last_time": "104716",
      "题材加成": 0.0,
      "板块": "农用机械"
    },
    {
      "rank": 38,
      "ts_code": "002382.SZ",
      "name": "蓝帆医疗",
      "board": "医疗保健",
      "StrengthScore": 62.694915,
      "ThemeBoost": 0.2601553699246989,
      "prob_rule": 0.6470802139125076,
      "prob_ml": 0.04093561783384069,
      "prob_final": 0.04093561783384069,
      "Probability": 0.04093561783384069,
      "final_score": 0.1740567140163577,
      "score": 0.1740567140163577,
      "prob": 0.04093561783384069,
      "strength01": 0.6269491500000001,
      "theme01": 0.20011951532669145,
      "trade_date": "20260313",
      "seal_amount": 87250829.0,
      "open_times": 0.0,
      "turnover_rate": 7.6814,
      "prob_src": "ml",
      "prob_ml_available": true,
      "prob_fusion_mode": "ml_first",
      "run_mode": "auto_daily",
      "run_time_utc": "2026-03-15T08:11:01Z",
      "industry": "医疗保健",
      "limit_type": "U",
      "close": "7.59",
      "up_limit": "7.59",
      "down_limit": "6.21",
      "fd_amount": "87250829.0",
      "first_time": "94654",
      "last_time": "94654",
      "题材加成": 0.2601553699246989,
      "板块": "医疗保健"
    },
    {
      "rank": 39,
      "ts_code": "002531.SZ",
      "name": "天顺风能",
      "board": "电气设备",
      "StrengthScore": 47.813559,
      "ThemeBoost": 0.7946272018253463,
      "prob_rule": 0.6950258852426787,
      "prob_ml": 0.02224004305965201,
      "prob_final": 0.02224004305965201,
      "Probability": 0.02224004305965201,
      "final_score": 0.17232031751293694,
      "score": 0.17232031751293694,
      "prob": 0.02224004305965201,
      "strength01": 0.47813559,
      "theme01": 0.6112516937118049,
      "trade_date": "20260313",
      "seal_amount": 87460360.0,
      "open_times": 0.0,
      "turnover_rate": 13.0208,
      "prob_src": "ml",
      "prob_ml_available": true,
      "prob_fusion_mode": "ml_first",
      "run_mode": "auto_daily",
      "run_time_utc": "2026-03-15T08:11:01Z",
      "industry": "电气设备",
      "limit_type": "U",
      "close": "12.42",
      "up_limit": "12.42",
      "down_limit": "10.16",
      "fd_amount": "87460360.0",
      "first_time": "101909",
      "last_time": "101909",
      "题材加成": 0.7946272018253463,
      "板块": "电气设备"
    },
    {
      "rank": 40,
      "ts_code": "600683.SH",
      "name": "京投发展",
      "board": "区域地产",
      "StrengthScore": 59.20339,
      "ThemeBoost": 0.08,
      "prob_rule": 0.6276885097341329,
      "prob_ml": 0.06516065139117652,
      "prob_final": 0.06516065139117652,
      "Probability": 0.06516065139117652,
      "final_score": 0.17017308212766974,
      "score": 0.17017308212766974,
      "prob": 0.06516065139117652,
      "strength01": 0.5920339,
      "theme01": 0.061538461538461535,
      "trade_date": "20260313",
      "seal_amount": 50816278.0,
      "open_times": 1.0,
      "turnover_rate": 13.2429,
      "prob_src": "ml",
      "prob_ml_available": true,
      "prob_fusion_mode": "ml_first",
      "run_mode": "auto_daily",
      "run_time_utc": "2026-03-15T08:11:01Z",
      "industry": "区域地产",
      "limit_type": "U",
      "close": "8.76",
      "up_limit": "8.76",
      "down_limit": "7.16",
      "fd_amount": "50816278.0",
      "first_time": "95822",
      "last_time": "100710",
      "题材加成": 0.08,
      "板块": "区域地产"
    },
    {
      "rank": 41,
      "ts_code": "600370.SH",
      "name": "三房巷",
      "board": "化工原料",
      "StrengthScore": 39.338983,
      "ThemeBoost": 1.0,
      "prob_rule": 0.6107494006929244,
      "prob_ml": 0.018884054595206902,
      "prob_final": 0.018884054595206902,
      "Probability": 0.018884054595206902,
      "final_score": 0.1688198811397218,
      "score": 0.1688198811397218,
      "prob": 0.018884054595206902,
      "strength01": 0.39338983,
      "theme01": 0.7692307692307692,
      "trade_date": "20260313",
      "seal_amount": 21947207.0,
      "open_times": 0.0,
      "turnover_rate": 37.5351,
      "prob_src": "ml",
      "prob_ml_available": true,
      "prob_fusion_mode": "ml_first",
      "run_mode": "auto_daily",
      "run_time_utc": "2026-03-15T08:11:01Z",
      "industry": "化工原料",
      "limit_type": "U",
      "close": "2.73",
      "up_limit": "2.73",
      "down_limit": "2.23",
      "fd_amount": "21947207.0",
      "first_time": "143221",
      "last_time": "143221",
      "题材加成": 1.0,
      "板块": "化工原料"
    },
    {
      "rank": 42,
      "ts_code": "002950.SZ",
      "name": "奥美医疗",
      "board": "医疗保健",
      "StrengthScore": 61.779661,
      "ThemeBoost": 0.2601553699246989,
      "prob_rule": 0.6401401499233363,
      "prob_ml": 0.029564232863462842,
      "prob_final": 0.029564232863462842,
      "Probability": 0.029564232863462842,
      "final_score": 0.16426623653709316,
      "score": 0.16426623653709316,
      "prob": 0.029564232863462842,
      "strength01": 0.61779661,
      "theme01": 0.20011951532669145,
      "trade_date": "20260313",
      "seal_amount": 63920845.0,
      "open_times": 0.0,
      "turnover_rate": 7.2237,
      "prob_src": "ml",
      "prob_ml_available": true,
      "prob_fusion_mode": "ml_first",
      "run_mode": "auto_daily",
      "run_time_utc": "2026-03-15T08:11:01Z",
      "industry": "医疗保健",
      "limit_type": "U",
      "close": "11.3",
      "up_limit": "11.3",
      "down_limit": "9.24",
      "fd_amount": "63920845.0",
      "first_time": "101427",
      "last_time": "101427",
      "题材加成": 0.2601553699246989,
      "板块": "医疗保健"
    },
    {
      "rank": 43,
      "ts_code": "002429.SZ",
      "name": "兆驰股份",
      "board": "家用电器",
      "StrengthScore": 41.627119,
      "ThemeBoost": 0.7030854212758787,
      "prob_rule": 0.584195271338079,
      "prob_ml": 0.033534946705566,
      "prob_final": 0.033534946705566,
      "Probability": 0.033534946705566,
      "final_score": 0.1608121946381946,
      "score": 0.1608121946381946,
      "prob": 0.033534946705566,
      "strength01": 0.41627119,
      "theme01": 0.5408349394429836,
      "trade_date": "20260313",
      "seal_amount": 60194423.0,
      "open_times": 5.0,
      "turnover_rate": 18.8401,
      "prob_src": "ml",
      "prob_ml_available": true,
      "prob_fusion_mode": "ml_first",
      "run_mode": "auto_daily",
      "run_time_utc": "2026-03-15T08:11:01Z",
      "industry": "家用电器",
      "limit_type": "U",
      "close": "11.94",
      "up_limit": "11.94",
      "down_limit": "9.77",
      "fd_amount": "60194423.0",
      "first_time": "94757",
      "last_time": "145418",
      "题材加成": 0.7030854212758787,
      "板块": "家用电器"
    },
    {
      "rank": 44,
      "ts_code": "003041.SZ",
      "name": "真爱美家",
      "board": "纺织",
      "StrengthScore": 54.542373,
      "ThemeBoost": 0.08,
      "prob_rule": 0.5003769336226187,
      "prob_ml": 0.05519948502954153,
      "prob_final": 0.05519948502954153,
      "Probability": 0.05519948502954153,
      "final_score": 0.15387823167452525,
      "score": 0.15387823167452525,
      "prob": 0.05519948502954153,
      "strength01": 0.54542373,
      "theme01": 0.061538461538461535,
      "trade_date": "20260313",
      "seal_amount": 7053453.0,
      "open_times": 3.0,
      "turnover_rate": 34.5191,
      "prob_src": "ml",
      "prob_ml_available": true,
      "prob_fusion_mode": "ml_first",
      "run_mode": "auto_daily",
      "run_time_utc": "2026-03-15T08:11:01Z",
      "industry": "纺织",
      "limit_type": "U",
      "close": "69.85",
      "up_limit": "69.85",
      "down_limit": "57.15",
      "fd_amount": "7053453.0",
      "first_time": "140157",
      "last_time": "144351",
      "题材加成": 0.08,
      "板块": "纺织"
    },
    {
      "rank": 45,
      "ts_code": "600232.SH",
      "name": "金鹰股份",
      "board": "纺织机械",
      "StrengthScore": 66.559322,
      "ThemeBoost": 0.0,
      "prob_rule": 0.6247846930247769,
      "prob_ml": 0.02884982193852448,
      "prob_final": 0.02884982193852448,
      "Probability": 0.02884982193852448,
      "final_score": 0.1533135193569672,
      "score": 0.1533135193569672,
      "prob": 0.02884982193852448,
      "strength01": 0.66559322,
      "theme01": 0.0,
      "trade_date": "20260313",
      "seal_amount": 57330766.0,
      "open_times": 0.0,
      "turnover_rate": 7.312,
      "prob_src": "ml",
      "prob_ml_available": true,
      "prob_fusion_mode": "ml_first",
      "run_mode": "auto_daily",
      "run_time_utc": "2026-03-15T08:11:01Z",
      "industry": "纺织机械",
      "limit_type": "U",
      "close": "8.78",
      "up_limit": "8.78",
      "down_limit": "7.18",
      "fd_amount": "57330766.0",
      "first_time": "100655",
      "last_time": "100655",
      "题材加成": 0.0,
      "板块": "纺织机械"
    },
    {
      "rank": 46,
      "ts_code": "603558.SH",
      "name": "健盛集团",
      "board": "纺织",
      "StrengthScore": 75.338983,
      "ThemeBoost": 0.0,
      "prob_rule": 0.6522844524127166,
      "prob_ml": 0.0031714922755916647,
      "prob_final": 0.0031714922755916647,
      "Probability": 0.0031714922755916647,
      "final_score": 0.1528980105929142,
      "score": 0.1528980105929142,
      "prob": 0.0031714922755916647,
      "strength01": 0.75338983,
      "theme01": 0.0,
      "trade_date": "20260313",
      "seal_amount": 41178949.0,
      "open_times": 0.0,
      "turnover_rate": 5.8478,
      "prob_src": "ml",
      "prob_ml_available": true,
      "prob_fusion_mode": "ml_first",
      "run_mode": "auto_daily",
      "run_time_utc": "2026-03-15T08:11:01Z",
      "industry": "纺织",
      "limit_type": "U",
      "close": "12.99",
      "up_limit": "12.99",
      "down_limit": "10.63",
      "fd_amount": "41178949.0",
      "first_time": "93327",
      "last_time": "93327",
      "题材加成": 0.0,
      "板块": "纺织"
    },
    {
      "rank": 47,
      "ts_code": "002903.SZ",
      "name": "宇环数控",
      "board": "机床制造",
      "StrengthScore": 55.237288,
      "ThemeBoost": 0.08,
      "prob_rule": 0.4640383211059527,
      "prob_ml": 0.0483544677089773,
      "prob_final": 0.0483544677089773,
      "Probability": 0.0483544677089773,
      "final_score": 0.1504765495501303,
      "score": 0.1504765495501303,
      "prob": 0.0483544677089773,
      "strength01": 0.55237288,
      "theme01": 0.061538461538461535,
      "trade_date": "20260313",
      "seal_amount": 3497081.0,
      "open_times": 4.0,
      "turnover_rate": 47.0035,
      "prob_src": "ml",
      "prob_ml_available": true,
      "prob_fusion_mode": "ml_first",
      "run_mode": "auto_daily",
      "run_time_utc": "2026-03-15T08:11:01Z",
      "industry": "机床制造",
      "limit_type": "U",
      "close": "31.03",
      "up_limit": "31.03",
      "down_limit": "25.39",
      "fd_amount": "3497081.0",
      "first_time": "110345",
      "last_time": "145515",
      "题材加成": 0.08,
      "板块": "机床制造"
    },
    {
      "rank": 48,
      "ts_code": "603607.SH",
      "name": "京华激光",
      "board": "造纸",
      "StrengthScore": 68.457627,
      "ThemeBoost": 0.0,
      "prob_rule": 0.6555748668446681,
      "prob_ml": 0.015568437328466288,
      "prob_final": 0.015568437328466288,
      "Probability": 0.015568437328466288,
      "final_score": 0.1478131601299264,
      "score": 0.1478131601299264,
      "prob": 0.015568437328466288,
      "strength01": 0.68457627,
      "theme01": 0.0,
      "trade_date": "20260313",
      "seal_amount": 36246111.0,
      "open_times": 0.0,
      "turnover_rate": 10.5553,
      "prob_src": "ml",
      "prob_ml_available": true,
      "prob_fusion_mode": "ml_first",
      "run_mode": "auto_daily",
      "run_time_utc": "2026-03-15T08:11:01Z",
      "industry": "造纸",
      "limit_type": "U",
      "close": "24.55",
      "up_limit": "24.55",
      "down_limit": "20.09",
      "fd_amount": "36246111.0",
      "first_time": "93520",
      "last_time": "93520",
      "题材加成": 0.0,
      "板块": "造纸"
    },
    {
      "rank": 49,
      "ts_code": "603062.SH",
      "name": "麦加芯彩",
      "board": "染料涂料",
      "StrengthScore": 54.084746,
      "ThemeBoost": 0.0,
      "prob_rule": 0.6091074488024073,
      "prob_ml": 0.04872486584821376,
      "prob_final": 0.04872486584821376,
      "Probability": 0.04872486584821376,
      "final_score": 0.14227689809374966,
      "score": 0.14227689809374966,
      "prob": 0.04872486584821376,
      "strength01": 0.5408474600000001,
      "theme01": 0.0,
      "trade_date": "20260313",
      "seal_amount": 101394332.0,
      "open_times": 0.0,
      "turnover_rate": 12.6463,
      "prob_src": "ml",
      "prob_ml_available": true,
      "prob_fusion_mode": "ml_first",
      "run_mode": "auto_daily",
      "run_time_utc": "2026-03-15T08:11:01Z",
      "industry": "染料涂料",
      "limit_type": "U",
      "close": "56.29",
      "up_limit": "56.29",
      "down_limit": "46.05",
      "fd_amount": "101394332.0",
      "first_time": "110928",
      "last_time": "110928",
      "题材加成": 0.0,
      "板块": "染料涂料"
    },
    {
      "rank": 50,
      "ts_code": "603248.SH",
      "name": "锡华科技",
      "board": "机械基件",
      "StrengthScore": 54.050847,
      "ThemeBoost": 0.2566570212508551,
      "prob_rule": 0.5279205110614337,
      "prob_ml": 0.015601459632883546,
      "prob_final": 0.015601459632883546,
      "Probability": 0.015601459632883546,
      "final_score": 0.13876556353154584,
      "score": 0.13876556353154584,
      "prob": 0.015601459632883546,
      "strength01": 0.54050847,
      "theme01": 0.19742847788527315,
      "trade_date": "20260313",
      "seal_amount": 17474637.0,
      "open_times": 2.0,
      "turnover_rate": 46.3969,
      "prob_src": "ml",
      "prob_ml_available": true,
      "prob_fusion_mode": "ml_first",
      "run_mode": "auto_daily",
      "run_time_utc": "2026-03-15T08:11:01Z",
      "industry": "机械基件",
      "limit_type": "U",
      "close": "28.2",
      "up_limit": "28.2",
      "down_limit": "23.08",
      "fd_amount": "17474637.0",
      "first_time": "130024",
      "last_time": "150000",
      "题材加成": 0.2566570212508551,
      "板块": "机械基件"
    },
    {
      "rank": 51,
      "ts_code": "603280.SH",
      "name": "南方路机",
      "board": "工程机械",
      "StrengthScore": 43.745763,
      "ThemeBoost": 0.18691333790156167,
      "prob_rule": 0.5469438349774554,
      "prob_ml": 0.05072717380605285,
      "prob_final": 0.05072717380605285,
      "Probability": 0.05072717380605285,
      "final_score": 0.13737849673358793,
      "score": 0.13737849673358793,
      "prob": 0.05072717380605285,
      "strength01": 0.43745763,
      "theme01": 0.14377949069350898,
      "trade_date": "20260313",
      "seal_amount": 336438410.0,
      "open_times": 0.0,
      "turnover_rate": 29.9117,
      "prob_src": "ml",
      "prob_ml_available": true,
      "prob_fusion_mode": "ml_first",
      "run_mode": "auto_daily",
      "run_time_utc": "2026-03-15T08:11:01Z",
      "industry": "工程机械",
      "limit_type": "U",
      "close": "40.7",
      "up_limit": "40.7",
      "down_limit": "33.3",
      "fd_amount": "336438410.0",
      "first_time": "110830",
      "last_time": "110830",
      "题材加成": 0.18691333790156167,
      "板块": "工程机械"
    },
    {
      "rank": 52,
      "ts_code": "600756.SH",
      "name": "浪潮软件",
      "board": "软件服务",
      "StrengthScore": 58.186441,
      "ThemeBoost": 0.0,
      "prob_rule": 0.6014080882644416,
      "prob_ml": 0.028285877757938685,
      "prob_final": 0.028285877757938685,
      "Probability": 0.028285877757938685,
      "final_score": 0.1361729964305571,
      "score": 0.1361729964305571,
      "prob": 0.028285877757938685,
      "strength01": 0.58186441,
      "theme01": 0.0,
      "trade_date": "20260313",
      "seal_amount": 99110571.0,
      "open_times": 1.0,
      "turnover_rate": 11.493,
      "prob_src": "ml",
      "prob_ml_available": true,
      "prob_fusion_mode": "ml_first",
      "run_mode": "auto_daily",
      "run_time_utc": "2026-03-15T08:11:01Z",
      "industry": "软件服务",
      "limit_type": "U",
      "close": "17.63",
      "up_limit": "17.63",
      "down_limit": "14.43",
      "fd_amount": "99110571.0",
      "first_time": "130830",
      "last_time": "130951",
      "题材加成": 0.0,
      "板块": "软件服务"
    },
    {
      "rank": 53,
      "ts_code": "603366.SH",
      "name": "日出东方",
      "board": "家用电器",
      "StrengthScore": 39.067797,
      "ThemeBoost": 0.6230854212758787,
      "prob_rule": 0.6152826412778728,
      "prob_ml": 0.006100635787961905,
      "prob_final": 0.006100635787961905,
      "Probability": 0.006100635787961905,
      "final_score": 0.13033568684202557,
      "score": 0.13033568684202557,
      "prob": 0.006100635787961905,
      "strength01": 0.39067797,
      "theme01": 0.47929647790452207,
      "trade_date": "20260313",
      "seal_amount": 75301314.0,
      "open_times": 0.0,
      "turnover_rate": 25.8867,
      "prob_src": "ml",
      "prob_ml_available": true,
      "prob_fusion_mode": "ml_first",
      "run_mode": "auto_daily",
      "run_time_utc": "2026-03-15T08:11:01Z",
      "industry": "家用电器",
      "limit_type": "U",
      "close": "10.32",
      "up_limit": "10.32",
      "down_limit": "8.44",
      "fd_amount": "75301314.0",
      "first_time": "103220",
      "last_time": "103220",
      "题材加成": 0.6230854212758787,
      "板块": "家用电器"
    },
    {
      "rank": 54,
      "ts_code": "002969.SZ",
      "name": "嘉美包装",
      "board": "广告包装",
      "StrengthScore": 46.694915,
      "ThemeBoost": 0.08,
      "prob_rule": 0.6068103583502098,
      "prob_ml": 0.03447919567774303,
      "prob_final": 0.03447919567774303,
      "Probability": 0.03447919567774303,
      "final_score": 0.1236791131282663,
      "score": 0.1236791131282663,
      "prob": 0.03447919567774303,
      "strength01": 0.46694915000000004,
      "theme01": 0.061538461538461535,
      "trade_date": "20260313",
      "seal_amount": 25932156.0,
      "open_times": 0.0,
      "turnover_rate": 18.7455,
      "prob_src": "ml",
      "prob_ml_available": true,
      "prob_fusion_mode": "ml_first",
      "run_mode": "auto_daily",
      "run_time_utc": "2026-03-15T08:11:01Z",
      "industry": "广告包装",
      "limit_type": "U",
      "close": "26.47",
      "up_limit": "26.47",
      "down_limit": "21.65",
      "fd_amount": "25932156.0",
      "first_time": "145600",
      "last_time": "145600",
      "题材加成": 0.08,
      "板块": "广告包装"
    },
    {
      "rank": 55,
      "ts_code": "600226.SH",
      "name": "亨通股份",
      "board": "供气供热",
      "StrengthScore": 53.0,
      "ThemeBoost": 0.08,
      "prob_rule": 0.5794144307476697,
      "prob_ml": 0.004955288277779548,
      "prob_final": 0.004955288277779548,
      "Probability": 0.004955288277779548,
      "final_score": 0.11562254794829185,
      "score": 0.11562254794829185,
      "prob": 0.004955288277779548,
      "strength01": 0.53,
      "theme01": 0.061538461538461535,
      "trade_date": "20260313",
      "seal_amount": 19367429.0,
      "open_times": 1.0,
      "turnover_rate": 9.8765,
      "prob_src": "ml",
      "prob_ml_available": true,
      "prob_fusion_mode": "ml_first",
      "run_mode": "auto_daily",
      "run_time_utc": "2026-03-15T08:11:01Z",
      "industry": "供气供热",
      "limit_type": "U",
      "close": "6.02",
      "up_limit": "6.02",
      "down_limit": "4.92",
      "fd_amount": "19367429.0",
      "first_time": "133335",
      "last_time": "134732",
      "题材加成": 0.08,
      "板块": "供气供热"
    },
    {
      "rank": 56,
      "ts_code": "603803.SH",
      "name": "瑞斯康达",
      "board": "通信设备",
      "StrengthScore": 43.474576,
      "ThemeBoost": 0.0,
      "prob_rule": 0.5049451472794795,
      "prob_ml": 0.018401662641036008,
      "prob_final": 0.018401662641036008,
      "Probability": 0.018401662641036008,
      "final_score": 0.09983031584872522,
      "score": 0.09983031584872522,
      "prob": 0.018401662641036008,
      "strength01": 0.43474576,
      "theme01": 0.0,
      "trade_date": "20260313",
      "seal_amount": 92794707.0,
      "open_times": 0.0,
      "turnover_rate": 32.6884,
      "prob_src": "ml",
      "prob_ml_available": true,
      "prob_fusion_mode": "ml_first",
      "run_mode": "auto_daily",
      "run_time_utc": "2026-03-15T08:11:01Z",
      "industry": "通信设备",
      "limit_type": "U",
      "close": "13.75",
      "up_limit": "13.75",
      "down_limit": "11.25",
      "fd_amount": "92794707.0",
      "first_time": "95315",
      "last_time": "95315",
      "题材加成": 0.0,
      "板块": "通信设备"
    },
    {
      "rank": 57,
      "ts_code": "600408.SH",
      "name": "安泰集团",
      "board": "焦炭加工",
      "StrengthScore": 39.542373,
      "ThemeBoost": 0.08,
      "prob_rule": 0.5454475421472101,
      "prob_ml": 0.008339023685759516,
      "prob_final": 0.008339023685759516,
      "Probability": 0.008339023685759516,
      "final_score": 0.09107590873387782,
      "score": 0.09107590873387782,
      "prob": 0.008339023685759516,
      "strength01": 0.39542373,
      "theme01": 0.061538461538461535,
      "trade_date": "20260313",
      "seal_amount": 59933263.0,
      "open_times": 0.0,
      "turnover_rate": 25.4106,
      "prob_src": "ml",
      "prob_ml_available": true,
      "prob_fusion_mode": "ml_first",
      "run_mode": "auto_daily",
      "run_time_utc": "2026-03-15T08:11:01Z",
      "industry": "焦炭加工",
      "limit_type": "U",
      "close": "4.13",
      "up_limit": "4.13",
      "down_limit": "3.38",
      "fd_amount": "59933263.0",
      "first_time": "105448",
      "last_time": "105448",
      "题材加成": 0.08,
      "板块": "焦炭加工"
    },
    {
      "rank": 58,
      "ts_code": "600726.SH",
      "name": "华电能源",
      "board": "火力发电",
      "StrengthScore": 34.389831,
      "ThemeBoost": 0.08,
      "prob_rule": 0.4674315779459,
      "prob_ml": 0.017547284986661155,
      "prob_final": 0.017547284986661155,
      "Probability": 0.017547284986661155,
      "final_score": 0.08721660764450896,
      "score": 0.08721660764450896,
      "prob": 0.017547284986661155,
      "strength01": 0.34389831,
      "theme01": 0.061538461538461535,
      "trade_date": "20260313",
      "seal_amount": 76517524.0,
      "open_times": 0.0,
      "turnover_rate": 35.5018,
      "prob_src": "ml",
      "prob_ml_available": true,
      "prob_fusion_mode": "ml_first",
      "run_mode": "auto_daily",
      "run_time_utc": "2026-03-15T08:11:01Z",
      "industry": "火力发电",
      "limit_type": "U",
      "close": "4.27",
      "up_limit": "4.27",
      "down_limit": "3.49",
      "fd_amount": "76517524.0",
      "first_time": "100655",
      "last_time": "100655",
      "题材加成": 0.08,
      "板块": "火力发电"
    },
    {
      "rank": 59,
      "ts_code": "300185.SZ",
      "name": "通裕重工",
      "board": "工程机械",
      "StrengthScore": 23.983051,
      "ThemeBoost": 0.18691333790156167,
      "prob_rule": 0.4752804771036494,
      "prob_ml": 0.018100673423631794,
      "prob_final": 0.018100673423631794,
      "Probability": 0.018100673423631794,
      "final_score": 0.07501452246589317,
      "score": 0.07501452246589317,
      "prob": 0.018100673423631794,
      "strength01": 0.23983051,
      "theme01": 0.14377949069350898,
      "trade_date": "20260313",
      "seal_amount": 250666372.0,
      "open_times": 0.0,
      "turnover_rate": 28.1829,
      "prob_src": "ml",
      "prob_ml_available": true,
      "prob_fusion_mode": "ml_first",
      "run_mode": "auto_daily",
      "run_time_utc": "2026-03-15T08:11:01Z",
      "industry": "工程机械",
      "limit_type": "U",
      "close": "4.21",
      "up_limit": "4.21",
      "down_limit": "2.81",
      "fd_amount": "250666372.0",
      "first_time": "104803",
      "last_time": "104803",
      "题材加成": 0.18691333790156167,
      "板块": "工程机械"
    }
  ],
  "limit_up_table": [],
  "learn": {
    "updated": false,
    "run_mode": "auto_daily",
    "reason": "entry_train_not_triggered"
  },
  "metrics": {
    "hit_count": 10,
    "top_count": 10,
    "limit_count": 59,
    "hit_rate": "100%"
  },
  "run_meta": {
    "run_id": "23106446895",
    "run_attempt": "1",
    "commit_sha": "a099810b8082b27a1c027dff82efc5ca43f807ed",
    "generated_at_utc": "2026-03-15T08:11:01Z"
  }
}